python_drawio/__init__.py
python_drawio/element.py
python_drawio/line.py
python_drawio/rectangle.py
python_drawio-0.1.2.dist-info/METADATA
python_drawio-0.1.2.dist-info/WHEEL
python_drawio-0.1.2.dist-info/top_level.txt
python_drawio-0.1.2.dist-info/RECORD
