Metadata-Version: 2.1
Name: python-drawio
Version: 0.1.2
Summary: Draw.io, with Python
Home-page: https://github.com/widespot/python-drawio/
Author: Raphaël JOIE
Author-email: info@widespot.be
